[
  {
    "firstName": "Juan",
    "lastName": "Perez",
    "email": "jperez@gmail.com",
    "password": 1234,
    "avatar": "default.png",
    "type": "admin",
    "id": 1
  },
  {
    "firstName": "Carlos",
    "lastName": "Rodriguez",
    "email": "carlitos@gmail.com",
    "password": 34325,
    "avatar": "default.png",
    "type": "client",
    "id": 2
  },
  {
    "firstName": "Esteban",
    "lastName": "Quito",
    "email": "banquito@hotmail.com",
    "password": 213123,
    "avatar": "default.png",
    "type": "client",
    "id": 3
  },
  {
    "firstName": "Eduardo",
    "lastName": "Hernandez",
    "email": "hernandez_eduardo@yahoo.com",
    "password": 587867,
    "avatar": "default.png",
    "type": "client",
    "id": 4
  },
  {
    "firstName": "Nicolás",
    "lastName": "Cilio",
    "email": "nicolasagustincilio@gmail.com",
    "password": "123",
    "avatar": "/img/users/logo4.png",
    "type": "client",
    "id": 5
  },
  {
    "firstName": "Nicolino",
    "lastName": "Cilio",
    "email": "nnnicolasagustincilio@gmail.com",
    "password": "$2b$10$B0JRUon1WFS1ZhFDLOQ84enINyYPWOq1PDcihaCKdjZfx9er/tdSW",
    "avatar": "/img/users/logo4.png",
    "type": "client",
    "id": 6
  }
]